{
  "format_version": "1.8.0",
  "animations": {
    "animation.minior.form_change_meteor": {
      "animation_length": 1.875,
      "bones": {
        "shell_2": {
          "rotation": {
            "0.0": [
              0,
              0,
              0
            ],
            "0.0417": {
              "pre": [
                -2,
                0,
                0
              ],
              "post": [
                -2,
                0,
                0
              ],
              "lerp_mode": "catmullrom"
            },
            "0.0833": [
              -15,
              0,
              25
            ],
            "0.125": [
              -15,
              0,
              25
            ],
            "0.375": [
              -15,
              0,
              -90
            ]
          },
          "position": {
            "0.0": [
              0,
              4,
              0
            ],
            "0.0417": {
              "pre": [
                0,
                5,
                1
              ],
              "post": [
                0,
                5,
                1
              ],
              "lerp_mode": "catmullrom"
            },
            "0.0833": [
              0,
              5,
              1
            ],
            "0.1667": [
              -1,
              9,
              1
            ],
            "0.25": {
              "pre": [
                -6,
                8,
                4
              ],
              "post": [
                -6,
                8,
                4
              ],
              "lerp_mode": "catmullrom"
            },
            "0.375": [
              -10,
              -2,
              11
            ],
            "0.4583": [
              -10,
              -1.5,
              11
            ],
            "0.5417": [
              -10,
              -2,
              11
            ],
            "1.7083": [
              -10,
              -2,
              11
            ],
            "1.875": [
              -10,
              -7.5,
              11
            ]
          },
          "scale": {
            "0.0": [
              1,
              1,
              1
            ],
            "1.7083": [
              1,
              1,
              1
            ],
            "1.875": [
              0,
              0,
              0
            ]
          }
        },
        "core": {
          "rotation": {
            "0.0": [
              0,
              0,
              0
            ],
            "0.0417": {
              "pre": [
                -2,
                0,
                0
              ],
              "post": [
                -2,
                0,
                0
              ],
              "lerp_mode": "catmullrom"
            },
            "0.0833": {
              "post": [
                -15,
                0,
                25
              ],
              "lerp_mode": "catmullrom"
            },
            "0.5": [
              0,
              0,
              0
            ],
            "0.5417": {
              "pre": [
                -2,
                0,
                0
              ],
              "post": [
                -2,
                0,
                0
              ],
              "lerp_mode": "catmullrom"
            },
            "0.5833": {
              "post": [
                -15,
                0,
                -10
              ],
              "lerp_mode": "catmullrom"
            },
            "1.0": [
              0,
              0,
              0
            ],
            "1.0417": {
              "pre": [
                -2,
                0,
                0
              ],
              "post": [
                -2,
                0,
                0
              ],
              "lerp_mode": "catmullrom"
            },
            "1.0833": {
              "post": [
                -15,
                0,
                0
              ],
              "lerp_mode": "catmullrom"
            },
            "1.4167": {
              "post": [
                5,
                0,
                0
              ],
              "lerp_mode": "catmullrom"
            },
            "1.7083": {
              "post": [
                1,
                0,
                0
              ],
              "lerp_mode": "catmullrom"
            },
            "1.875": [
              0,
              0,
              0
            ]
          },
          "position": {
            "0.0": [
              0,
              4,
              0
            ],
            "0.0417": {
              "pre": [
                0,
                5,
                1
              ],
              "post": [
                0,
                5,
                1
              ],
              "lerp_mode": "catmullrom"
            },
            "0.5": [
              0,
              4,
              0
            ],
            "0.5417": {
              "pre": [
                0,
                5,
                1
              ],
              "post": [
                0,
                5,
                1
              ],
              "lerp_mode": "catmullrom"
            },
            "1.0": [
              0,
              4,
              0
            ],
            "1.0417": {
              "pre": [
                0,
                5,
                1
              ],
              "post": [
                0,
                5,
                1
              ],
              "lerp_mode": "catmullrom"
            },
            "1.5": {
              "post": [
                0,
                3.5,
                0.5
              ],
              "lerp_mode": "catmullrom"
            },
            "1.7083": {
              "post": [
                0,
                4,
                0
              ],
              "lerp_mode": "catmullrom"
            }
          }
        },
        "mouth": {
          "scale": {
            "1.2083": [
              0,
              0,
              0
            ],
            "1.375": {
              "pre": [
                0.9,
                0.9,
                0.9
              ],
              "post": [
                0.9,
                0.9,
                0.9
              ],
              "lerp_mode": "catmullrom"
            },
            "1.6667": [
              1,
              1,
              1
            ]
          }
        },
        "eyes": {
          "position": [
            0,
            0,
            0
          ],
          "scale": {
            "1.2083": [
              0,
              0,
              0
            ],
            "1.375": {
              "pre": [
                0.9,
                0.9,
                0.9
              ],
              "post": [
                0.9,
                0.9,
                0.9
              ],
              "lerp_mode": "catmullrom"
            },
            "1.6667": [
              1,
              1,
              1
            ]
          }
        },
        "shell_1": {
          "rotation": {
            "0.0": [
              0,
              0,
              0
            ],
            "0.0417": {
              "pre": [
                -2,
                0,
                0
              ],
              "post": [
                -2,
                0,
                0
              ],
              "lerp_mode": "catmullrom"
            },
            "0.0833": {
              "post": [
                -15,
                0,
                25
              ],
              "lerp_mode": "catmullrom"
            },
            "0.5": [
              0,
              0,
              0
            ],
            "0.5417": {
              "pre": [
                -2,
                0,
                0
              ],
              "post": [
                -2,
                0,
                0
              ],
              "lerp_mode": "catmullrom"
            },
            "0.5833": {
              "post": [
                -15,
                0,
                -10
              ],
              "lerp_mode": "catmullrom"
            },
            "1.0": [
              0,
              0,
              0
            ],
            "1.0417": {
              "pre": [
                -2,
                0,
                0
              ],
              "post": [
                -2,
                0,
                0
              ],
              "lerp_mode": "catmullrom"
            },
            "1.0833": [
              -15,
              0,
              0
            ],
            "1.125": [
              -15,
              0,
              0
            ],
            "1.4583": {
              "pre": [
                -90,
                0,
                0
              ],
              "post": [
                -90,
                0,
                0
              ],
              "lerp_mode": "catmullrom"
            }
          },
          "position": {
            "0.0": [
              0,
              4,
              0
            ],
            "0.0417": {
              "pre": [
                0,
                5,
                1
              ],
              "post": [
                0,
                5,
                1
              ],
              "lerp_mode": "catmullrom"
            },
            "0.5": [
              0,
              4,
              0
            ],
            "0.5417": {
              "pre": [
                0,
                5,
                1
              ],
              "post": [
                0,
                5,
                1
              ],
              "lerp_mode": "catmullrom"
            },
            "1.0": [
              0,
              4,
              0
            ],
            "1.0417": {
              "pre": [
                0,
                5,
                1
              ],
              "post": [
                0,
                5,
                1
              ],
              "lerp_mode": "catmullrom"
            },
            "1.0833": [
              0,
              5,
              1
            ],
            "1.1667": [
              0,
              10,
              3
            ],
            "1.2917": {
              "pre": [
                0,
                10,
                9
              ],
              "post": [
                0,
                10,
                9
              ],
              "lerp_mode": "catmullrom"
            },
            "1.4583": [
              0,
              -2,
              14
            ],
            "1.5417": [
              0,
              -1.5,
              14
            ],
            "1.7083": [
              0,
              -2,
              14
            ],
            "1.875": [
              0,
              -7.5,
              14
            ]
          },
          "scale": {
            "1.7083": [
              1,
              1,
              1
            ],
            "1.875": [
              0,
              0,
              0
            ]
          }
        },
        "shell_3": {
          "rotation": {
            "0.0": [
              0,
              0,
              0
            ],
            "0.0417": {
              "pre": [
                -2,
                0,
                0
              ],
              "post": [
                -2,
                0,
                0
              ],
              "lerp_mode": "catmullrom"
            },
            "0.0833": {
              "post": [
                -15,
                0,
                25
              ],
              "lerp_mode": "catmullrom"
            },
            "0.5": [
              0,
              0,
              0
            ],
            "0.5417": {
              "pre": [
                -2,
                0,
                0
              ],
              "post": [
                -2,
                0,
                0
              ],
              "lerp_mode": "catmullrom"
            },
            "0.5833": {
              "post": [
                -15,
                0,
                -10
              ],
              "lerp_mode": "catmullrom"
            },
            "1.0": [
              0,
              0,
              0
            ],
            "1.0417": {
              "pre": [
                -2,
                0,
                0
              ],
              "post": [
                -2,
                0,
                0
              ],
              "lerp_mode": "catmullrom"
            },
            "1.0833": [
              -15,
              0,
              0
            ],
            "1.1667": [
              -15,
              0,
              0
            ],
            "1.3333": [
              0,
              0,
              0
            ]
          },
          "position": {
            "0.0": [
              0,
              4,
              0
            ],
            "0.0417": {
              "pre": [
                0,
                5,
                1
              ],
              "post": [
                0,
                5,
                1
              ],
              "lerp_mode": "catmullrom"
            },
            "0.5": [
              0,
              4,
              0
            ],
            "0.5417": {
              "pre": [
                0,
                5,
                1
              ],
              "post": [
                0,
                5,
                1
              ],
              "lerp_mode": "catmullrom"
            },
            "1.0": [
              0,
              4,
              0
            ],
            "1.0417": {
              "pre": [
                0,
                5,
                1
              ],
              "post": [
                0,
                5,
                1
              ],
              "lerp_mode": "catmullrom"
            },
            "1.0833": [
              0,
              5,
              1
            ],
            "1.125": [
              -1,
              4,
              1
            ],
            "1.2083": {
              "pre": [
                -4,
                2,
                0
              ],
              "post": [
                -4,
                2,
                0
              ],
              "lerp_mode": "catmullrom"
            },
            "1.3333": [
              -7,
              -2,
              -1
            ],
            "1.4167": [
              -7,
              -1.5,
              -1
            ],
            "1.5": [
              -7,
              -2,
              -1
            ],
            "1.7083": [
              -7,
              -2,
              -1
            ],
            "1.875": [
              -9,
              -7.5,
              -1
            ]
          },
          "scale": {
            "1.7083": [
              1,
              1,
              1
            ],
            "1.875": [
              0,
              0,
              0
            ]
          }
        },
        "shell_4": {
          "rotation": {
            "0.0": [
              0,
              0,
              0
            ],
            "0.0417": {
              "pre": [
                -2,
                0,
                0
              ],
              "post": [
                -2,
                0,
                0
              ],
              "lerp_mode": "catmullrom"
            },
            "0.0833": {
              "post": [
                -15,
                0,
                25
              ],
              "lerp_mode": "catmullrom"
            },
            "0.5": [
              0,
              0,
              0
            ],
            "0.5417": {
              "pre": [
                -2,
                0,
                0
              ],
              "post": [
                -2,
                0,
                0
              ],
              "lerp_mode": "catmullrom"
            },
            "0.5833": [
              -15,
              0,
              -10
            ],
            "0.6667": [
              -15,
              0,
              -10
            ],
            "0.8333": [
              0,
              0,
              0
            ]
          },
          "position": {
            "0.0": [
              0,
              4,
              0
            ],
            "0.0417": {
              "pre": [
                0,
                5,
                1
              ],
              "post": [
                0,
                5,
                1
              ],
              "lerp_mode": "catmullrom"
            },
            "0.5": [
              0,
              4,
              0
            ],
            "0.5417": {
              "pre": [
                0,
                5,
                1
              ],
              "post": [
                0,
                5,
                1
              ],
              "lerp_mode": "catmullrom"
            },
            "0.5833": [
              0,
              5,
              1
            ],
            "0.625": [
              3,
              5,
              1
            ],
            "0.75": {
              "pre": [
                6,
                2,
                1
              ],
              "post": [
                6,
                2,
                1
              ],
              "lerp_mode": "catmullrom"
            },
            "0.8333": [
              7,
              -2,
              1
            ],
            "0.9167": [
              7,
              -1.5,
              1
            ],
            "1.0": [
              7,
              -2,
              1
            ],
            "1.7083": [
              7,
              -2,
              1
            ],
            "1.875": [
              7.5,
              -7.5,
              1
            ]
          },
          "scale": {
            "1.7083": [
              1,
              1,
              1
            ],
            "1.875": [
              0,
              0,
              0
            ]
          }
        }
      }
    },
    "animation.minior.ground_idle": {
      "loop": true,
      "animation_length": 4,
      "bones": {
        "torso": {
          "rotation": [
            0,
            0,
            "-q.anim_time*90"
          ],
          "position": [
            "0+math.sin(q.anim_time*90*2)*2",
            "0-math.sin(q.anim_time*90*4)*1",
            0
          ]
        },
        "mouth": {
          "position": [
            "0+math.sin(q.anim_time*90*2)*2.3",
            "0-math.sin(q.anim_time*90*4)*1",
            0
          ]
        },
        "eyes": {
          "position": [
            "0+math.sin(q.anim_time*90*2)*2.3",
            "0-math.sin(q.anim_time*90*4)*1",
            0
          ]
        },
        "armor": {
          "rotation": [
            0,
            0,
            "-q.anim_time*90"
          ],
          "position": [
            "0+math.sin(q.anim_time*90*2)*2",
            "0-math.sin(q.anim_time*90*4)*1",
            0
          ]
        },
        "body": {
          "position": [
            0,
            4,
            0
          ]
        }
      }
    },
    "animation.minior.ground_walk": {
      "loop": true,
      "animation_length": 4,
      "bones": {
        "body": {
          "rotation": [
            10,
            0,
            0
          ],
          "position": [
            0,
            4,
            0
          ]
        },
        "torso": {
          "rotation": [
            0,
            0,
            "-q.anim_time*90"
          ],
          "position": [
            "0+math.sin(q.anim_time*90*2)*2",
            "0-math.sin(q.anim_time*90*4)*2.5",
            0
          ]
        },
        "mouth": {
          "position": [
            "0+math.sin(q.anim_time*90*2)*2.3",
            "0-math.sin(q.anim_time*90*4)*2.5",
            0
          ]
        },
        "eyes": {
          "position": [
            "0+math.sin(q.anim_time*90*2)*2.3",
            "0-math.sin(q.anim_time*90*4)*2.5",
            0
          ]
        },
        "armor": {
          "rotation": [
            0,
            0,
            "-q.anim_time*90"
          ],
          "position": [
            "0+math.sin(q.anim_time*90*2)*2",
            "0-math.sin(q.anim_time*90*4)*2.5",
            0
          ]
        }
      }
    },
    "animation.minior.ground_run": {
      "loop": true,
      "animation_length": 8,
      "bones": {
        "body": {
          "rotation": [
            15,
            0,
            0
          ],
          "position": [
            0,
            4,
            0
          ]
        },
        "torso": {
          "rotation": [
            0,
            0,
            "-q.anim_time*135"
          ],
          "position": [
            "0+math.sin(q.anim_time*90*2)*2.5",
            "0-math.sin(q.anim_time*90*4)*2.5",
            0
          ]
        },
        "mouth": {
          "position": [
            "0+math.sin(q.anim_time*90*2)*2.8",
            "0-math.sin(q.anim_time*90*4)*2.5",
            0
          ]
        },
        "eyes": {
          "position": [
            "0+math.sin(q.anim_time*90*2)*2.8",
            "0-math.sin(q.anim_time*90*4)*2.5",
            0
          ]
        },
        "armor": {
          "rotation": [
            0,
            0,
            "-q.anim_time*135"
          ],
          "position": [
            "0+math.sin(q.anim_time*90*2)*2.5",
            "0-math.sin(q.anim_time*90*4)*2.5",
            0
          ]
        },
        "pupil_right": {
          "position": [
            0,
            0.15,
            0
          ]
        },
        "pupil_left": {
          "position": [
            0,
            0.15,
            0
          ]
        }
      }
    },
    "animation.minior.battle_idle": {
      "loop": true,
      "animation_length": 4,
      "bones": {
        "torso": {
          "rotation": [
            0,
            0,
            "-q.anim_time*90"
          ],
          "position": [
            "0+math.sin(q.anim_time*90*2)*2",
            "0-math.sin(q.anim_time*90*4)*1",
            0
          ]
        },
        "mouth": {
          "position": [
            "0+math.sin(q.anim_time*90*2)*2.3",
            "0-math.sin(q.anim_time*90*4)*1",
            0
          ]
        },
        "eyes": {
          "position": [
            "0+math.sin(q.anim_time*90*2)*2.3",
            "0-math.sin(q.anim_time*90*4)*1",
            0
          ]
        },
        "armor": {
          "rotation": [
            0,
            0,
            "-q.anim_time*90"
          ],
          "position": [
            "0+math.sin(q.anim_time*90*2)*2",
            "0-math.sin(q.anim_time*90*4)*1",
            0
          ]
        },
        "body": {
          "position": [
            0,
            4,
            0
          ]
        },
        "pupil_right": {
          "rotation": [
            0,
            0,
            15
          ],
          "position": [
            0,
            0,
            0
          ],
          "scale": 1
        },
        "pupil_left": {
          "rotation": [
            0,
            0,
            -15
          ],
          "position": [
            0,
            0,
            0
          ],
          "scale": 1
        }
      }
    },
    "animation.minior.cry": {
      "animation_length": 1.5833,
      "bones": {
        "body": {
          "rotation": {
            "0.0": [
              0,
              0,
              0
            ],
            "0.1667": [
              2.5,
              0,
              0
            ],
            "0.25": {
              "pre": [
                -10,
                0,
                0
              ],
              "post": [
                -10,
                0,
                0
              ],
              "lerp_mode": "catmullrom"
            },
            "0.375": {
              "post": [
                -5,
                0,
                0
              ],
              "lerp_mode": "catmullrom"
            },
            "0.7083": [
              -21,
              0,
              0
            ],
            "1.125": {
              "pre": [
                -17,
                0,
                0
              ],
              "post": [
                -17,
                0,
                0
              ],
              "lerp_mode": "catmullrom"
            },
            "1.2917": {
              "post": [
                0,
                0,
                0
              ],
              "lerp_mode": "catmullrom"
            },
            "1.5": [
              0,
              0,
              0
            ]
          },
          "position": {
            "0.0": [
              0,
              0,
              0
            ],
            "0.0833": [
              0,
              1,
              0
            ],
            "0.2083": [
              0,
              0.75,
              0
            ],
            "0.2917": [
              0,
              0.92,
              0
            ],
            "0.3333": [
              0,
              0.97,
              0
            ],
            "0.4167": [
              0,
              1,
              0
            ],
            "0.5833": [
              "0+math.sin(query.anim_time*90*10*5)*0.2",
              1,
              0
            ],
            "0.9583": [
              0,
              0,
              0
            ],
            "1.2083": {
              "pre": [
                0,
                0,
                0
              ],
              "post": [
                0,
                0,
                0
              ],
              "lerp_mode": "catmullrom"
            },
            "1.5": [
              0,
              0,
              0
            ]
          }
        },
        "mouth_right": {
          "rotation": {
            "0.0": [
              0,
              0,
              0
            ],
            "0.0833": {
              "pre": [
                0,
                0,
                -21.25
              ],
              "post": [
                0,
                0,
                -21.25
              ],
              "lerp_mode": "catmullrom"
            },
            "0.125": {
              "post": [
                0,
                0,
                -21.25
              ],
              "lerp_mode": "catmullrom"
            },
            "0.2083": {
              "post": [
                0,
                0,
                -21.25
              ],
              "lerp_mode": "catmullrom"
            },
            "1.375": {
              "post": [
                0,
                0,
                -21.25
              ],
              "lerp_mode": "catmullrom"
            },
            "1.4583": {
              "post": [
                0,
                0,
                -21.25
              ],
              "lerp_mode": "catmullrom"
            },
            "1.5417": [
              0,
              0,
              0
            ]
          },
          "position": {
            "0.0": [
              0,
              0,
              0
            ],
            "0.0833": {
              "pre": [
                0,
                -0.15,
                0
              ],
              "post": [
                0,
                -0.15,
                0
              ],
              "lerp_mode": "catmullrom"
            },
            "0.125": {
              "post": [
                0,
                -0.15,
                0
              ],
              "lerp_mode": "catmullrom"
            },
            "0.2083": {
              "post": [
                0,
                -0.15,
                0
              ],
              "lerp_mode": "catmullrom"
            },
            "0.3333": [
              0.8,
              -0.15,
              0
            ],
            "0.4167": [
              0.8,
              -0.65,
              0
            ],
            "1.0833": [
              0.8,
              -0.65,
              0
            ],
            "1.125": [
              0.8,
              -0.65,
              0
            ],
            "1.2083": [
              0.8,
              -0.15,
              0
            ],
            "1.375": {
              "pre": [
                0.8,
                -0.15,
                0
              ],
              "post": [
                0.8,
                -0.15,
                0
              ],
              "lerp_mode": "catmullrom"
            },
            "1.4583": {
              "post": [
                0,
                -0.15,
                0
              ],
              "lerp_mode": "catmullrom"
            },
            "1.5417": [
              0,
              0,
              0
            ]
          }
        },
        "mouth_left": {
          "rotation": {
            "0.0": [
              0,
              0,
              0
            ],
            "0.0833": {
              "pre": [
                0,
                0,
                21.25
              ],
              "post": [
                0,
                0,
                21.25
              ],
              "lerp_mode": "catmullrom"
            },
            "0.125": {
              "post": [
                0,
                0,
                21.25
              ],
              "lerp_mode": "catmullrom"
            },
            "0.2083": {
              "post": [
                0,
                0,
                21.25
              ],
              "lerp_mode": "catmullrom"
            },
            "1.375": {
              "post": [
                0,
                0,
                21.87
              ],
              "lerp_mode": "catmullrom"
            },
            "1.4583": {
              "post": [
                0,
                0,
                21.25
              ],
              "lerp_mode": "catmullrom"
            },
            "1.5417": [
              0,
              0,
              0
            ]
          },
          "position": {
            "0.0": [
              0,
              0,
              0
            ],
            "0.0833": {
              "pre": [
                0,
                -0.15,
                0
              ],
              "post": [
                0,
                -0.15,
                0
              ],
              "lerp_mode": "catmullrom"
            },
            "0.125": {
              "post": [
                0,
                -0.15,
                0
              ],
              "lerp_mode": "catmullrom"
            },
            "0.2083": {
              "post": [
                0,
                -0.15,
                0
              ],
              "lerp_mode": "catmullrom"
            },
            "0.3333": [
              -0.8,
              -0.15,
              0
            ],
            "0.4167": [
              -0.8,
              0.35,
              0
            ],
            "1.0833": [
              -0.8,
              0.35,
              0
            ],
            "1.125": [
              -0.8,
              0.35,
              0
            ],
            "1.2083": [
              -0.8,
              -0.15,
              0
            ],
            "1.375": {
              "pre": [
                -0.8,
                -0.15,
                0
              ],
              "post": [
                -0.8,
                -0.15,
                0
              ],
              "lerp_mode": "catmullrom"
            },
            "1.4583": {
              "post": [
                0,
                -0.15,
                0
              ],
              "lerp_mode": "catmullrom"
            },
            "1.5417": [
              0,
              0,
              0
            ]
          }
        }
      },
      "sound_effects": {
        "0.4167": {
          "effect": "pokemon.minior.cry"
        }
      }
    },
    "animation.minior.blink": {
      "animation_length": 0.125,
      "bones": {
        "pupil_right": {
          "position": {
            "0.0": [
              0,
              0,
              0
            ],
            "0.0417": [
              0,
              0,
              0
            ]
          },
          "scale": {
            "0.0": [
              1,
              1,
              1
            ],
            "0.0417": [
              1,
              0.5,
              1
            ]
          }
        },
        "pupil_left": {
          "position": {
            "0.0": [
              0,
              0,
              0
            ],
            "0.0417": [
              0,
              0,
              0
            ]
          },
          "scale": {
            "0.0": [
              1,
              1,
              1
            ],
            "0.0417": [
              1,
              0.5,
              1
            ]
          }
        }
      }
    },
    "animation.minior.sleep": {
      "loop": true,
      "animation_length": 4,
      "bones": {
        "torso": {
          "rotation": [
            0,
            0,
            "-q.anim_time*90"
          ],
          "position": [
            "0+math.sin(q.anim_time*45*2)*2",
            "0-math.sin(q.anim_time*45*4)*1",
            0
          ]
        },
        "mouth": {
          "position": [
            "0+math.sin(q.anim_time*45*2)*2.3",
            "0-math.sin(q.anim_time*45*4)*1",
            0
          ]
        },
        "eyes": {
          "position": [
            "0+math.sin(q.anim_time*45*2)*2.3",
            "00-math.sin(q.anim_time*45*4)*1",
            0
          ]
        },
        "armor": {
          "rotation": [
            0,
            0,
            "-q.anim_time*90"
          ],
          "position": [
            "0+math.sin(q.anim_time*45*2)*2",
            "0-math.sin(q.anim_time*45*4)*1",
            0
          ]
        },
        "body": {
          "position": [
            0,
            4,
            0
          ]
        },
        "pupil_right": {
          "scale": [
            1,
            0.5,
            1
          ]
        },
        "pupil_left": {
          "scale": [
            1,
            0.5,
            1
          ]
        }
      }
    },
    "animation.minior.recoil": {
      "animation_length": 1,
      "bones": {
        "body": {
          "rotation": {
            "0.0": [
              0,
              0,
              0
            ],
            "0.0417": {
              "pre": [
                -2,
                0,
                0
              ],
              "post": [
                -2,
                0,
                0
              ],
              "lerp_mode": "catmullrom"
            },
            "0.0833": {
              "post": [
                -15,
                0,
                0
              ],
              "lerp_mode": "catmullrom"
            },
            "0.4167": {
              "post": [
                5,
                0,
                0
              ],
              "lerp_mode": "catmullrom"
            },
            "0.7083": {
              "post": [
                1,
                0,
                0
              ],
              "lerp_mode": "catmullrom"
            },
            "0.875": {
              "post": [
                0,
                0,
                0
              ],
              "lerp_mode": "catmullrom"
            },
            "1.0": [
              0,
              0,
              0
            ]
          },
          "position": {
            "0.0": [
              0,
              0,
              0
            ],
            "0.0417": {
              "pre": [
                0,
                1,
                2
              ],
              "post": [
                0,
                1,
                2
              ],
              "lerp_mode": "catmullrom"
            },
            "0.5": {
              "post": [
                0,
                -0.5,
                0.5
              ],
              "lerp_mode": "catmullrom"
            },
            "0.7083": {
              "post": [
                0,
                0,
                0
              ],
              "lerp_mode": "catmullrom"
            }
          }
        },
        "mouth_right": {
          "rotation": {
            "0.0417": [
              0,
              0,
              0
            ],
            "0.0833": {
              "pre": [
                0,
                0,
                -21.25
              ],
              "post": [
                0,
                0,
                -21.25
              ],
              "lerp_mode": "catmullrom"
            },
            "0.125": [
              0,
              0,
              -47.11
            ],
            "0.75": [
              0,
              0,
              -45
            ],
            "0.7917": {
              "pre": [
                0,
                0,
                -21.25
              ],
              "post": [
                0,
                0,
                -21.25
              ],
              "lerp_mode": "catmullrom"
            },
            "0.875": [
              0,
              0,
              0
            ]
          },
          "position": {
            "0.0417": [
              0,
              0,
              0
            ],
            "0.0833": {
              "pre": [
                0.055,
                -0.15,
                0
              ],
              "post": [
                0.055,
                -0.15,
                0
              ],
              "lerp_mode": "catmullrom"
            },
            "0.125": [
              0.05,
              -0.32,
              0
            ],
            "0.75": [
              0.03,
              -0.32,
              0
            ],
            "0.7917": {
              "pre": [
                0.055,
                -0.15,
                0
              ],
              "post": [
                0.055,
                -0.15,
                0
              ],
              "lerp_mode": "catmullrom"
            },
            "0.875": [
              0,
              0,
              0
            ]
          }
        },
        "mouth_left": {
          "rotation": {
            "0.0417": [
              0,
              0,
              0
            ],
            "0.0833": {
              "pre": [
                0,
                0,
                21.25
              ],
              "post": [
                0,
                0,
                21.25
              ],
              "lerp_mode": "catmullrom"
            },
            "0.125": [
              0,
              0,
              47.11
            ],
            "0.75": [
              0,
              0,
              45
            ],
            "0.7917": {
              "pre": [
                0,
                0,
                21.25
              ],
              "post": [
                0,
                0,
                21.25
              ],
              "lerp_mode": "catmullrom"
            },
            "0.875": [
              0,
              0,
              0
            ]
          },
          "position": {
            "0.0417": [
              0,
              0,
              0
            ],
            "0.0833": {
              "pre": [
                -0.055,
                -0.15,
                0
              ],
              "post": [
                -0.055,
                -0.15,
                0
              ],
              "lerp_mode": "catmullrom"
            },
            "0.125": [
              -0.05,
              -0.32,
              0
            ],
            "0.75": [
              -0.02,
              -0.32,
              0
            ],
            "0.7917": [
              -0.055,
              -0.15,
              0
            ],
            "0.875": [
              0,
              0,
              0
            ]
          }
        },
        "pupil_left": {
          "rotation": {
            "0.0417": [
              0,
              0,
              0
            ],
            "0.0833": {
              "pre": [
                0,
                0,
                22.5
              ],
              "post": [
                0,
                0,
                22.5
              ],
              "lerp_mode": "catmullrom"
            },
            "0.75": {
              "post": [
                0,
                0,
                15
              ],
              "lerp_mode": "catmullrom"
            },
            "0.875": [
              0,
              0,
              0
            ]
          },
          "scale": {
            "0.0417": [
              1,
              1,
              1
            ],
            "0.0833": {
              "pre": [
                1,
                0.5,
                1
              ],
              "post": [
                1,
                0.5,
                1
              ],
              "lerp_mode": "catmullrom"
            },
            "0.75": {
              "post": [
                1,
                0.525,
                1
              ],
              "lerp_mode": "catmullrom"
            },
            "0.875": [
              1,
              1,
              1
            ]
          }
        },
        "pupil_right": {
          "rotation": {
            "0.0417": [
              0,
              0,
              0
            ],
            "0.0833": {
              "pre": [
                0,
                0,
                -22.5
              ],
              "post": [
                0,
                0,
                -22.5
              ],
              "lerp_mode": "catmullrom"
            },
            "0.75": {
              "post": [
                0,
                0,
                -15
              ],
              "lerp_mode": "catmullrom"
            },
            "0.875": [
              0,
              0,
              0
            ]
          },
          "scale": {
            "0.0417": [
              1,
              1,
              1
            ],
            "0.0833": {
              "pre": [
                1,
                0.5,
                1
              ],
              "post": [
                1,
                0.5,
                1
              ],
              "lerp_mode": "catmullrom"
            },
            "0.75": {
              "post": [
                1,
                0.5,
                1
              ],
              "lerp_mode": "catmullrom"
            },
            "0.875": [
              1,
              1,
              1
            ]
          }
        },
        "mouth": {
          "position": {
            "0.0417": [
              0,
              0,
              0
            ],
            "0.125": {
              "pre": [
                0,
                0.2,
                0
              ],
              "post": [
                0,
                0.2,
                0
              ],
              "lerp_mode": "catmullrom"
            },
            "0.1667": [
              0,
              0.2,
              0
            ],
            "0.7083": [
              0,
              0.2,
              0
            ],
            "0.75": {
              "pre": [
                0,
                0.2,
                0
              ],
              "post": [
                0,
                0.2,
                0
              ],
              "lerp_mode": "catmullrom"
            },
            "0.875": [
              0,
              0,
              0
            ]
          }
        }
      }
    },
    "animation.minior.faint": {
      "loop": "hold_on_last_frame",
      "animation_length": 5.5,
      "bones": {
        "body": {
          "rotation": {
            "0.0": [
              0,
              0,
              0
            ],
            "0.2083": [
              0,
              0,
              0
            ],
            "0.375": {
              "pre": [
                -5,
                0,
                0
              ],
              "post": [
                -5,
                0,
                0
              ],
              "lerp_mode": "catmullrom"
            },
            "0.75": [
              5,
              0,
              0
            ],
            "1.125": [
              90,
              0,
              0
            ]
          },
          "position": {
            "0.0": [
              0,
              4,
              0
            ],
            "0.0833": [
              0,
              -1,
              0
            ],
            "0.125": [
              0,
              -1.15,
              0
            ],
            "0.2083": {
              "pre": [
                0,
                -0.5,
                0
              ],
              "post": [
                0,
                -0.5,
                0
              ],
              "lerp_mode": "catmullrom"
            },
            "0.2917": [
              0,
              -1,
              0
            ],
            "0.3333": [
              "0+math.sin(query.anim_time*90*10*5)*0.5",
              -1,
              0
            ],
            "0.4583": [
              0.19,
              -1,
              0
            ],
            "0.7917": {
              "pre": [
                0,
                -1,
                -0.2
              ],
              "post": [
                0,
                -1,
                -0.2
              ],
              "lerp_mode": "catmullrom"
            },
            "0.9583": [
              0,
              1,
              -2
            ],
            "1.125": [
              0,
              -3,
              -6
            ],
            "1.2083": [
              0,
              -2.5,
              -6
            ],
            "1.2917": [
              0,
              -3,
              -6
            ]
          },
          "scale": {
            "0.0": [
              1,
              1,
              1
            ],
            "0.0833": [
              1,
              1,
              1
            ],
            "0.125": {
              "pre": [
                1,
                0.98,
                1
              ],
              "post": [
                1,
                0.98,
                1
              ],
              "lerp_mode": "catmullrom"
            },
            "0.2083": [
              1,
              1,
              1
            ]
          }
        },
        "mouth": {
          "position": [
            0,
            0.2,
            0
          ]
        },
        "mouth_right": {
          "rotation": {
            "0.0": [
              0,
              0,
              -47.11
            ],
            "0.0833": [
              0,
              0,
              -47.11
            ],
            "0.125": {
              "pre": [
                0,
                0,
                -21.25
              ],
              "post": [
                0,
                0,
                -21.25
              ],
              "lerp_mode": "catmullrom"
            },
            "1.0833": {
              "post": [
                0,
                0,
                -21.25
              ],
              "lerp_mode": "catmullrom"
            },
            "1.1667": [
              0,
              0,
              -47.11
            ],
            "1.25": [
              0,
              0,
              -47.11
            ]
          },
          "position": {
            "0.0": [
              0.05,
              -0.32,
              0
            ],
            "0.0833": [
              0.05,
              -0.32,
              0
            ],
            "0.125": [
              0,
              -0.15,
              0
            ],
            "0.1667": [
              0.8,
              -0.15,
              0
            ],
            "0.25": [
              0.8,
              -0.15,
              0
            ],
            "0.3333": {
              "pre": [
                0.8,
                -0.65,
                0
              ],
              "post": [
                0.8,
                -0.65,
                0
              ],
              "lerp_mode": "catmullrom"
            },
            "0.875": {
              "post": [
                0.8,
                -0.65,
                0
              ],
              "lerp_mode": "catmullrom"
            },
            "0.9583": [
              0.8,
              -0.15,
              0
            ],
            "1.0417": [
              0.8,
              -0.15,
              0
            ],
            "1.0833": [
              0,
              -0.15,
              0
            ],
            "1.1667": [
              0.05,
              -0.32,
              0
            ],
            "1.25": [
              0.05,
              -0.32,
              0
            ]
          }
        },
        "mouth_left": {
          "rotation": {
            "0.0": [
              0,
              0,
              47.11
            ],
            "0.0417": [
              0,
              0,
              47.11
            ],
            "0.125": {
              "pre": [
                0,
                0,
                21.25
              ],
              "post": [
                0,
                0,
                21.25
              ],
              "lerp_mode": "catmullrom"
            },
            "1.0833": {
              "post": [
                0,
                0,
                21.25
              ],
              "lerp_mode": "catmullrom"
            },
            "1.1667": [
              0,
              0,
              47.11
            ],
            "1.25": [
              0,
              0,
              47.11
            ]
          },
          "position": {
            "0.0": [
              -0.05,
              -0.32,
              0
            ],
            "0.0417": [
              -0.05,
              -0.32,
              0
            ],
            "0.125": [
              0,
              -0.15,
              0
            ],
            "0.1667": [
              -0.8,
              -0.15,
              0
            ],
            "0.25": [
              -0.8,
              -0.15,
              0
            ],
            "0.3333": {
              "pre": [
                -0.8,
                0.35,
                0
              ],
              "post": [
                -0.8,
                0.35,
                0
              ],
              "lerp_mode": "catmullrom"
            },
            "0.875": {
              "post": [
                -0.8,
                0.35,
                0
              ],
              "lerp_mode": "catmullrom"
            },
            "0.9583": [
              -0.8,
              -0.15,
              0
            ],
            "1.0417": [
              -0.8,
              -0.15,
              0
            ],
            "1.0833": [
              0,
              -0.15,
              0
            ],
            "1.1667": [
              -0.05,
              -0.32,
              0
            ],
            "1.25": [
              -0.05,
              -0.32,
              0
            ]
          }
        },
        "eye_right": {
          "rotation": {
            "0.0": [
              0,
              0,
              0
            ],
            "0.2083": [
              0,
              0,
              0
            ],
            "0.3333": [
              0,
              0,
              0
            ],
            "1.0": [
              0,
              0,
              350
            ],
            "1.0833": [
              0,
              0,
              360
            ]
          },
          "position": {
            "0.0": [
              0,
              0,
              0
            ],
            "0.2083": [
              0,
              0,
              0
            ],
            "0.3333": [
              0,
              0,
              0
            ],
            "0.5": {
              "pre": [
                0,
                0,
                0
              ],
              "post": [
                0,
                0,
                0
              ],
              "lerp_mode": "catmullrom"
            },
            "0.6667": {
              "post": [
                -1.25,
                -1,
                0
              ],
              "lerp_mode": "catmullrom"
            },
            "0.8333": {
              "post": [
                -1,
                -1,
                0
              ],
              "lerp_mode": "catmullrom"
            },
            "0.9583": [
              0,
              0,
              0
            ]
          }
        },
        "pupil_right": {
          "rotation": {
            "1.0833": [
              0,
              0,
              0
            ],
            "1.1667": {
              "pre": [
                0,
                0,
                -22.5
              ],
              "post": [
                0,
                0,
                -22.5
              ],
              "lerp_mode": "catmullrom"
            }
          },
          "scale": {
            "1.0833": [
              1,
              1,
              1
            ],
            "1.1667": {
              "pre": [
                1,
                0.5,
                1
              ],
              "post": [
                1,
                0.5,
                1
              ],
              "lerp_mode": "catmullrom"
            }
          }
        },
        "eye_left": {
          "rotation": {
            "0.0": [
              0,
              0,
              0
            ],
            "0.3333": [
              0,
              0,
              0
            ],
            "1.0": [
              0,
              0,
              350
            ],
            "1.0833": [
              0,
              0,
              360
            ]
          },
          "position": {
            "0.0": [
              0,
              0,
              0
            ],
            "0.3333": [
              0,
              0,
              0
            ],
            "0.5": {
              "pre": [
                0,
                0,
                0
              ],
              "post": [
                0,
                0,
                0
              ],
              "lerp_mode": "catmullrom"
            },
            "0.6667": {
              "post": [
                1.25,
                1,
                0
              ],
              "lerp_mode": "catmullrom"
            },
            "0.8333": {
              "post": [
                1,
                1,
                0
              ],
              "lerp_mode": "catmullrom"
            },
            "0.9583": [
              0,
              0,
              0
            ]
          }
        },
        "pupil_left": {
          "rotation": {
            "1.0833": [
              0,
              0,
              0
            ],
            "1.1667": {
              "pre": [
                0,
                0,
                22.5
              ],
              "post": [
                0,
                0,
                22.5
              ],
              "lerp_mode": "catmullrom"
            }
          },
          "scale": {
            "1.0833": [
              1,
              1,
              1
            ],
            "1.1667": {
              "pre": [
                1,
                0.5,
                1
              ],
              "post": [
                1,
                0.5,
                1
              ],
              "lerp_mode": "catmullrom"
            }
          }
        }
      }
    },
    "animation.minior.special": {
      "animation_length": 1.6667,
      "bones": {
        "body": {
          "rotation": {
            "0.0": [
              0,
              0,
              0
            ],
            "0.1667": {
              "pre": [
                2.5,
                0,
                0
              ],
              "post": [
                2.5,
                0,
                0
              ],
              "lerp_mode": "catmullrom"
            },
            "0.4167": {
              "post": [
                -5,
                0,
                0
              ],
              "lerp_mode": "catmullrom"
            },
            "0.7083": {
              "post": [
                -8,
                0,
                0
              ],
              "lerp_mode": "catmullrom"
            },
            "1.25": {
              "post": [
                -10,
                0,
                0
              ],
              "lerp_mode": "catmullrom"
            },
            "1.4583": {
              "post": [
                5,
                0,
                0
              ],
              "lerp_mode": "catmullrom"
            },
            "1.625": [
              0,
              0,
              0
            ]
          },
          "position": {
            "0.0": [
              0,
              0,
              0
            ],
            "0.0833": [
              0,
              0,
              0
            ],
            "0.2083": {
              "pre": [
                0,
                0.75,
                0
              ],
              "post": [
                0,
                0.75,
                0
              ],
              "lerp_mode": "catmullrom"
            },
            "0.2917": {
              "post": [
                0,
                0.2,
                0
              ],
              "lerp_mode": "catmullrom"
            },
            "0.3333": {
              "post": [
                0,
                0.07,
                0
              ],
              "lerp_mode": "catmullrom"
            },
            "0.4167": [
              0,
              1,
              0
            ],
            "0.5": [
              "0+math.sin(query.anim_time*90*10*5)*0.2",
              1,
              0
            ],
            "0.9583": [
              0,
              1,
              0
            ],
            "1.25": [
              "0+math.sin(query.anim_time*90*10*5)*0.05",
              0.7,
              0
            ],
            "1.3333": [
              0,
              0.6,
              0
            ],
            "1.4583": {
              "pre": [
                0,
                0.5,
                0
              ],
              "post": [
                0,
                0.5,
                0
              ],
              "lerp_mode": "catmullrom"
            },
            "1.625": [
              0,
              0,
              0
            ]
          }
        },
        "mouth_right": {
          "rotation": {
            "0.0": [
              0,
              0,
              0
            ],
            "0.0833": {
              "pre": [
                0,
                0,
                -21.25
              ],
              "post": [
                0,
                0,
                -21.25
              ],
              "lerp_mode": "catmullrom"
            },
            "0.125": {
              "post": [
                0,
                0,
                -21.25
              ],
              "lerp_mode": "catmullrom"
            },
            "1.4167": {
              "post": [
                0,
                0,
                -21.25
              ],
              "lerp_mode": "catmullrom"
            },
            "1.5": {
              "post": [
                0,
                0,
                -21.25
              ],
              "lerp_mode": "catmullrom"
            },
            "1.5833": [
              0,
              0,
              0
            ]
          },
          "position": {
            "0.0": [
              0,
              0,
              0
            ],
            "0.0833": {
              "pre": [
                0,
                -0.15,
                0
              ],
              "post": [
                0,
                -0.15,
                0
              ],
              "lerp_mode": "catmullrom"
            },
            "0.125": {
              "post": [
                0,
                -0.15,
                0
              ],
              "lerp_mode": "catmullrom"
            },
            "0.2083": [
              0.8,
              -0.15,
              0
            ],
            "0.2917": [
              0.8,
              -0.65,
              0
            ],
            "1.2083": [
              0.8,
              -0.65,
              0
            ],
            "1.25": [
              0.8,
              -0.65,
              0
            ],
            "1.3333": [
              0.8,
              -0.15,
              0
            ],
            "1.4167": {
              "pre": [
                0.8,
                -0.15,
                0
              ],
              "post": [
                0.8,
                -0.15,
                0
              ],
              "lerp_mode": "catmullrom"
            },
            "1.5": {
              "post": [
                0,
                -0.15,
                0
              ],
              "lerp_mode": "catmullrom"
            },
            "1.5833": [
              0,
              0,
              0
            ]
          }
        },
        "mouth_left": {
          "rotation": {
            "0.0": [
              0,
              0,
              0
            ],
            "0.0833": {
              "pre": [
                0,
                0,
                21.25
              ],
              "post": [
                0,
                0,
                21.25
              ],
              "lerp_mode": "catmullrom"
            },
            "0.125": {
              "post": [
                0,
                0,
                21.25
              ],
              "lerp_mode": "catmullrom"
            },
            "1.4167": {
              "post": [
                0,
                0,
                21.87
              ],
              "lerp_mode": "catmullrom"
            },
            "1.5": {
              "post": [
                0,
                0,
                21.25
              ],
              "lerp_mode": "catmullrom"
            },
            "1.5833": [
              0,
              0,
              0
            ]
          },
          "position": {
            "0.0": [
              0,
              0,
              0
            ],
            "0.0833": {
              "pre": [
                0,
                -0.15,
                0
              ],
              "post": [
                0,
                -0.15,
                0
              ],
              "lerp_mode": "catmullrom"
            },
            "0.125": {
              "post": [
                0,
                -0.15,
                0
              ],
              "lerp_mode": "catmullrom"
            },
            "0.2083": [
              -0.8,
              -0.15,
              0
            ],
            "0.2917": [
              -0.8,
              0.35,
              0
            ],
            "1.2083": [
              -0.8,
              0.35,
              0
            ],
            "1.25": [
              -0.8,
              0.35,
              0
            ],
            "1.3333": [
              -0.8,
              -0.15,
              0
            ],
            "1.4167": {
              "pre": [
                -0.8,
                -0.15,
                0
              ],
              "post": [
                -0.8,
                -0.15,
                0
              ],
              "lerp_mode": "catmullrom"
            },
            "1.5": {
              "post": [
                0,
                -0.15,
                0
              ],
              "lerp_mode": "catmullrom"
            },
            "1.5833": [
              0,
              0,
              0
            ]
          }
        },
        "eye_right": {
          "rotation": {
            "0.0": [
              0,
              0,
              0
            ],
            "0.2083": [
              0,
              0,
              0
            ],
            "0.3333": [
              0,
              0,
              0
            ],
            "1.2083": [
              0,
              0,
              350
            ],
            "1.2917": [
              0,
              0,
              360
            ]
          },
          "position": {
            "0.0": [
              0,
              0,
              0
            ],
            "0.2083": [
              0,
              0,
              0
            ],
            "0.3333": [
              0,
              0,
              0
            ],
            "0.5417": {
              "pre": [
                0,
                0,
                0
              ],
              "post": [
                0,
                0,
                0
              ],
              "lerp_mode": "catmullrom"
            },
            "0.7917": [
              -1.5,
              -1,
              0
            ],
            "1.0": {
              "pre": [
                -1,
                -0.5,
                0
              ],
              "post": [
                -1,
                -0.5,
                0
              ],
              "lerp_mode": "catmullrom"
            },
            "1.1667": [
              0,
              0,
              0
            ]
          }
        },
        "eye_left": {
          "rotation": {
            "0.0": [
              0,
              0,
              0
            ],
            "0.3333": [
              0,
              0,
              0
            ],
            "1.2083": [
              0,
              0,
              350
            ],
            "1.2917": [
              0,
              0,
              360
            ]
          },
          "position": {
            "0.0": [
              0,
              0,
              0
            ],
            "0.3333": [
              0,
              0,
              0
            ],
            "0.5417": {
              "pre": [
                0,
                0,
                0
              ],
              "post": [
                0,
                0,
                0
              ],
              "lerp_mode": "catmullrom"
            },
            "0.7917": [
              1.5,
              1,
              0
            ],
            "1.0": {
              "pre": [
                1,
                0.5,
                0
              ],
              "post": [
                1,
                0.5,
                0
              ],
              "lerp_mode": "catmullrom"
            },
            "1.1667": [
              0,
              0,
              0
            ]
          }
        },
        "pupil_right": {
          "rotation": {
            "0.2083": [
              0,
              0,
              0
            ],
            "0.3333": [
              0,
              0,
              -15
            ],
            "1.2917": [
              0,
              0,
              -15
            ],
            "1.4583": [
              0,
              0,
              0
            ]
          }
        },
        "pupil_left": {
          "rotation": {
            "0.2083": [
              0,
              0,
              0
            ],
            "0.3333": [
              0,
              0,
              15
            ],
            "1.2917": [
              0,
              0,
              15
            ],
            "1.4583": [
              0,
              0,
              0
            ]
          }
        }
      }
    },
    "animation.minior.attack": {
      "animation_length": 1.125,
      "bones": {
        "body": {
          "rotation": {
            "0.0": [
              0,
              0,
              0
            ],
            "0.0833": [
              -10,
              0,
              0
            ],
            "0.2917": {
              "pre": [
                -2,
                0,
                0
              ],
              "post": [
                -2,
                0,
                0
              ],
              "lerp_mode": "catmullrom"
            },
            "0.4167": [
              1.95,
              0,
              0
            ],
            "0.625": [
              8,
              0,
              0
            ],
            "0.875": [
              -3,
              0,
              0
            ],
            "1.0": [
              0,
              0,
              0
            ]
          },
          "position": {
            "0.0": [
              0,
              0,
              0
            ],
            "0.0417": {
              "pre": [
                0,
                1,
                0
              ],
              "post": [
                0,
                1,
                0
              ],
              "lerp_mode": "catmullrom"
            },
            "0.1667": {
              "post": [
                0,
                0.5,
                5
              ],
              "lerp_mode": "catmullrom"
            },
            "0.4583": [
              0,
              2.5,
              5.5
            ],
            "0.5417": {
              "pre": [
                0,
                1,
                -1.25
              ],
              "post": [
                0,
                1,
                -1.25
              ],
              "lerp_mode": "catmullrom"
            },
            "0.625": [
              0,
              2.5,
              -11
            ],
            "0.7083": {
              "pre": [
                0,
                2,
                -6
              ],
              "post": [
                0,
                2,
                -6
              ],
              "lerp_mode": "catmullrom"
            },
            "0.7917": [
              0,
              1,
              0
            ],
            "0.9167": {
              "pre": [
                0,
                0,
                3
              ],
              "post": [
                0,
                0,
                3
              ],
              "lerp_mode": "catmullrom"
            },
            "1.125": [
              0,
              0,
              0
            ]
          }
        },
        "mouth_right": {
          "rotation": {
            "0.0": [
              0,
              0,
              0
            ],
            "0.0833": [
              0,
              0,
              -21.25
            ],
            "0.9167": [
              0,
              0,
              -21.25
            ],
            "1.0": [
              0,
              0,
              0
            ]
          },
          "position": {
            "0.0": [
              0,
              0,
              0
            ],
            "0.0833": [
              0,
              -0.15,
              0
            ],
            "0.1667": [
              0.8,
              -0.15,
              0
            ],
            "0.4583": [
              0.8,
              -0.15,
              0
            ],
            "0.5417": [
              0.8,
              -0.65,
              0
            ],
            "0.7917": [
              0.8,
              -0.65,
              0
            ],
            "0.8333": [
              0.8,
              -0.15,
              0
            ],
            "0.9167": [
              0,
              -0.15,
              0
            ],
            "1.0": [
              0,
              0,
              0
            ]
          }
        },
        "mouth_left": {
          "rotation": {
            "0.0": [
              0,
              0,
              0
            ],
            "0.0833": [
              0,
              0,
              21.25
            ],
            "0.9167": [
              0,
              0,
              21.25
            ],
            "1.0": [
              0,
              0,
              0
            ]
          },
          "position": {
            "0.0": [
              0,
              0,
              0
            ],
            "0.0833": [
              0,
              -0.15,
              0
            ],
            "0.1667": [
              -0.8,
              -0.15,
              0
            ],
            "0.4583": [
              -0.8,
              -0.15,
              0
            ],
            "0.5417": [
              -0.8,
              0.35,
              0
            ],
            "0.7917": [
              -0.8,
              0.35,
              0
            ],
            "0.8333": [
              -0.8,
              -0.15,
              0
            ],
            "0.9167": [
              0,
              -0.15,
              0
            ],
            "1.0": [
              0,
              0,
              0
            ]
          }
        },
        "pupil_right": {
          "rotation": {
            "0.0": [
              0,
              0,
              0
            ],
            "0.4583": [
              0,
              0,
              0
            ],
            "0.5417": [
              0,
              0,
              22.5
            ],
            "0.8333": [
              0,
              0,
              22.5
            ],
            "0.9167": [
              0,
              0,
              0
            ]
          },
          "position": [
            0,
            0,
            0
          ],
          "scale": {
            "0.0": [
              1,
              1,
              1
            ],
            "0.4583": [
              1,
              1,
              1
            ],
            "0.5417": [
              1,
              0.5,
              1
            ],
            "0.8333": [
              1,
              0.5,
              1
            ],
            "0.9167": [
              1,
              1,
              1
            ]
          }
        },
        "pupil_left": {
          "rotation": {
            "0.0": [
              0,
              0,
              0
            ],
            "0.4583": [
              0,
              0,
              0
            ],
            "0.5417": [
              0,
              0,
              -22.5
            ],
            "0.8333": [
              0,
              0,
              -22.5
            ],
            "0.9167": [
              0,
              0,
              0
            ]
          },
          "position": [
            0,
            0,
            0
          ],
          "scale": {
            "0.0": [
              1,
              1,
              1
            ],
            "0.4583": [
              1,
              1,
              1
            ],
            "0.5417": [
              1,
              0.5,
              1
            ],
            "0.8333": [
              1,
              0.5,
              1
            ],
            "0.9167": [
              1,
              1,
              1
            ]
          }
        },
        "armor": {
          "rotation": {
            "0.0": [
              0,
              0,
              0
            ],
            "0.125": [
              0,
              0,
              0
            ],
            "0.3333": {
              "pre": [
                0,
                0,
                10
              ],
              "post": [
                0,
                0,
                10
              ],
              "lerp_mode": "catmullrom"
            },
            "0.5": [
              0,
              0,
              -10
            ],
            "0.6667": {
              "pre": [
                0,
                0,
                -60
              ],
              "post": [
                0,
                0,
                -60
              ],
              "lerp_mode": "catmullrom"
            },
            "0.9167": [
              0,
              0,
              0
            ],
            "1.0": [
              0,
              0,
              0
            ]
          }
        }
      }
    },
    "animation.minior.shoulder_right": {
      "loop": true,
      "animation_length": 4,
      "bones": {
        "torso": {
          "rotation": [
            0,
            0,
            "-q.anim_time*90"
          ],
          "position": [
            "0+math.sin(q.anim_time*90*2)*2",
            "0-math.sin(q.anim_time*90*4)*1",
            0
          ]
        },
        "mouth": {
          "position": [
            "0+math.sin(q.anim_time*90*2)*2.3",
            "0-math.sin(q.anim_time*90*4)*1",
            0
          ]
        },
        "eyes": {
          "position": [
            "0+math.sin(q.anim_time*90*2)*2.3",
            "0-math.sin(q.anim_time*90*4)*1",
            0
          ]
        },
        "armor": {
          "rotation": [
            0,
            0,
            "-q.anim_time*90"
          ],
          "position": [
            "0+math.sin(q.anim_time*90*2)*2",
            "0-math.sin(q.anim_time*90*4)*1",
            0
          ]
        },
        "body": {
          "position": [
            0,
            4,
            0
          ]
        }
      }
    },
    "animation.minior.shoulder_left": {
      "loop": true,
      "animation_length": 4,
      "bones": {
        "torso": {
          "rotation": [
            0,
            0,
            "-q.anim_time*90"
          ],
          "position": [
            "0+math.sin(q.anim_time*90*2)*2",
            "0-math.sin(q.anim_time*90*4)*1",
            0
          ]
        },
        "mouth": {
          "position": [
            "0+math.sin(q.anim_time*90*2)*2.3",
            "0-math.sin(q.anim_time*90*4)*1",
            0
          ]
        },
        "eyes": {
          "position": [
            "0+math.sin(q.anim_time*90*2)*2.3",
            "0-math.sin(q.anim_time*90*4)*1",
            0
          ]
        },
        "armor": {
          "rotation": [
            0,
            0,
            "-q.anim_time*90"
          ],
          "position": [
            "0+math.sin(q.anim_time*90*2)*2",
            "0-math.sin(q.anim_time*90*4)*1",
            0
          ]
        },
        "body": {
          "position": [
            0,
            4,
            0
          ]
        }
      }
    },
    "animation.minior.form_change": {
      "animation_length": 1.5,
      "bones": {
        "body": {
          "rotation": {
            "0.0": [
              0,
              0,
              0
            ],
            "0.4167": {
              "pre": [
                1,
                0,
                0
              ],
              "post": [
                1,
                0,
                0
              ],
              "lerp_mode": "catmullrom"
            },
            "1.1667": [
              -2,
              0,
              0
            ],
            "1.2083": [
              -5,
              0,
              0
            ],
            "1.2917": [
              5,
              0,
              0
            ],
            "1.5": [
              0,
              0,
              0
            ]
          },
          "position": {
            "0.0417": [
              0,
              4,
              0
            ],
            "0.5": {
              "pre": [
                0,
                3.5,
                0
              ],
              "post": [
                0,
                3.5,
                0
              ],
              "lerp_mode": "catmullrom"
            },
            "1.0833": [
              0,
              4.5,
              0
            ],
            "1.1667": [
              0,
              4.5,
              0
            ],
            "1.2083": [
              0,
              3.5,
              0
            ],
            "1.2917": [
              0,
              4.5,
              0
            ],
            "1.375": [
              0,
              4,
              0
            ]
          }
        },
        "mouth": {
          "scale": {
            "1.0": [
              1,
              1,
              1
            ],
            "1.125": {
              "pre": [
                0.8,
                0.8,
                0.8
              ],
              "post": [
                0.8,
                0.8,
                0.8
              ],
              "lerp_mode": "catmullrom"
            },
            "1.2083": [
              0,
              0,
              0
            ]
          }
        },
        "eyes": {
          "scale": {
            "1.0": [
              1,
              1,
              1
            ],
            "1.125": {
              "pre": [
                0.8,
                0.8,
                0.8
              ],
              "post": [
                0.8,
                0.8,
                0.8
              ],
              "lerp_mode": "catmullrom"
            },
            "1.2083": [
              0,
              0,
              0
            ]
          }
        },
        "shell_1": {
          "position": {
            "0.0": [
              9,
              1.75,
              0
            ],
            "0.9167": [
              9,
              1.75,
              0
            ],
            "1.0": {
              "pre": [
                8,
                1,
                0
              ],
              "post": [
                8,
                1,
                0
              ],
              "lerp_mode": "catmullrom"
            },
            "1.0833": [
              8,
              1,
              0
            ],
            "1.1667": [
              0,
              0,
              0
            ]
          },
          "scale": {
            "0.0": [
              0,
              0,
              0
            ],
            "0.9167": [
              0,
              0,
              0
            ],
            "1.0": {
              "pre": [
                1,
                1,
                1
              ],
              "post": [
                1,
                1,
                1
              ],
              "lerp_mode": "catmullrom"
            }
          }
        },
        "shell_2": {
          "position": {
            "0.0": [
              -9,
              1.75,
              0
            ],
            "0.9167": [
              -9,
              1.75,
              0
            ],
            "1.0": {
              "pre": [
                -6,
                1,
                0
              ],
              "post": [
                -6,
                1,
                0
              ],
              "lerp_mode": "catmullrom"
            },
            "1.0833": [
              -6,
              1,
              0
            ],
            "1.1667": [
              0,
              0,
              0
            ]
          },
          "scale": {
            "0.0": [
              0,
              0,
              0
            ],
            "0.9167": [
              0,
              0,
              0
            ],
            "1.0": {
              "pre": [
                1,
                1,
                1
              ],
              "post": [
                1,
                1,
                1
              ],
              "lerp_mode": "catmullrom"
            }
          }
        },
        "shell_3": {
          "position": {
            "0.0": [
              -4,
              -4,
              0
            ],
            "0.9167": [
              -6,
              -6,
              0
            ],
            "1.0": {
              "pre": [
                -3,
                -4,
                0
              ],
              "post": [
                -3,
                -4,
                0
              ],
              "lerp_mode": "catmullrom"
            },
            "1.0833": [
              -3,
              -4,
              0
            ],
            "1.1667": [
              0,
              0,
              0
            ]
          },
          "scale": {
            "0.0": [
              0,
              0,
              0
            ],
            "0.9167": [
              0,
              0,
              0
            ],
            "1.0": {
              "pre": [
                1,
                1,
                1
              ],
              "post": [
                1,
                1,
                1
              ],
              "lerp_mode": "catmullrom"
            }
          }
        },
        "shell_4": {
          "position": {
            "0.0": [
              7,
              -7,
              0
            ],
            "0.9167": [
              7,
              -7,
              0
            ],
            "1.0": {
              "pre": [
                3,
                -3,
                0
              ],
              "post": [
                3,
                -3,
                0
              ],
              "lerp_mode": "catmullrom"
            },
            "1.0833": [
              3,
              -3,
              0
            ],
            "1.1667": [
              0,
              0,
              0
            ]
          },
          "scale": {
            "0.0": [
              0,
              0,
              0
            ],
            "0.9167": [
              0,
              0,
              0
            ],
            "1.0": {
              "pre": [
                1,
                1,
                1
              ],
              "post": [
                1,
                1,
                1
              ],
              "lerp_mode": "catmullrom"
            }
          }
        }
      }
    }
  }
}