{
  "portraitScale": 0.96,
  "portraitTranslation": [
    -0.35,
    0.71,
    0.0
  ],
  "profileScale": 0.57,
  "profileTranslation": [
    -0.11,
    0.73,
    0.0
  ],
  "animations": {
    "cry": "q.bedrock_stateful('darmanitan_galar', 'cry')"
  },
  "poses": {
    "battle-standing": {
      "transformTicks": 10,
      "poseTypes": [
        "STAND",
        "WALK"
      ],
      "isBattle": true,
      "animations": [
        "q.look('head')",
        "q.bedrock('darmanitan_galar', 'battle_idle')"
      ],
      "quirks": [
        "q.bedrock_quirk('darmanitan_galar', 'blink')"
      ]
    },
    "standing": {
      "transformTicks": 10,
      "poseTypes": [
        "STAND",
        "NONE",
        "PORTRAIT",
        "PROFILE"
      ],
      "isBattle": false,
      "animations": [
        "q.look('head')",
        "q.bedrock('darmanitan_galar', 'ground_idle')"
      ],
      "quirks": [
        "q.bedrock_quirk('darmanitan_galar', 'blink')"
      ]
    },
    "walking": {
      "transformTicks": 8,
      "poseTypes": [
        "WALK"
      ],
      "animations": [
        "q.look('head')",
        "q.bedrock('darmanitan_galar', 'ground_walk')"
      ],
      "quirks": [
        "q.bedrock_quirk('darmanitan_galar', 'blink')"
      ]
    },
    "hover": {
      "transformTicks": 5,
      "poseTypes": [
        "FLY",
        "HOVER",
        "FLOAT"
      ],
      "animations": [
        "q.look('head')",
        "q.bedrock('darmanitan_galar', 'ground_walk')"
      ],
      "quirks": [
        "q.bedrock_quirk('darmanitan_galar', 'blink')"
      ]
    },
    "float": {
      "transformTicks": 5,
      "poseTypes": [
        "FLOAT"
      ],
      "animations": [
        "q.look('head')",
        "q.bedrock('darmanitan_galar', 'ground_walk')"
      ],
      "quirks": [
        "q.bedrock_quirk('darmanitan_galar', 'blink')"
      ]
    },
    "swim": {
      "transformTicks": 8,
      "poseTypes": [
        "SWIM"
      ],
      "animations": [
        "q.look('head')",
        "q.bedrock('darmanitan_galar', 'ground_walk')"
      ],
      "quirks": [
        "q.bedrock_quirk('darmanitan_galar', 'blink')"
      ]
    }
  }
}